tabsra/__init__.py
tabsra/skorch_tabsra.py
skorch_tabsra-0.0.1.dist-info/LICENSE
skorch_tabsra-0.0.1.dist-info/METADATA
skorch_tabsra-0.0.1.dist-info/WHEEL
skorch_tabsra-0.0.1.dist-info/top_level.txt
skorch_tabsra-0.0.1.dist-info/RECORD
