Metadata-Version: 2.1
Name: skorch_tabsra
Version: 0.0.1
Summary: TabSRA model
Author-email: Kodjo Mawuena AMEKOE <amekoekodjomawuena@gmail.com>
License: Apache License
Project-URL: Homepage, https://github.com/anselmeamekoe/pytabsra
Project-URL: Issues, https://github.com/anselmeamekoe/pytabsra/issues
Classifier: Programming Language :: Python :: 3
Classifier: Operating System :: OS Independent
Requires-Python: >=3.9
License-File: LICENSE
Requires-Dist: numpy >=1.21.0
Requires-Dist: torch >=1.12.1
Requires-Dist: einops >=0.4.1
Requires-Dist: skorch >=0.15.0
